hffastup/__init__.py
hffastup/push_utils.py
hf_fastup-0.0.7.dist-info/METADATA
hf_fastup-0.0.7.dist-info/WHEEL
hf_fastup-0.0.7.dist-info/top_level.txt
hf_fastup-0.0.7.dist-info/RECORD
