Metadata-Version: 2.1
Name: hf-fastup
Version: 0.0.7
Summary: Fast upload in parallel large datasets to HuggingFace Datasets hub.
Home-page: https://github.com/kkoutini/hf-fastup
Author: Khaled Koutini
Author-email: first.last@jku.at
License: Apache-2.0
Project-URL: Bug Tracker, https://github.com/kkoutini/hf-fastup/issues
Project-URL: Source Code, https://github.com/kkoutini/hf-fastup
Requires-Python: >=3.7
Requires-Dist: datasets >=2.15.0
Requires-Dist: hf-transfer >=0.1.4
